anhaltai/__init__.py
anhaltai/gbif_downloader/__init__.py
anhaltai/gbif_downloader/config.py
anhaltai/gbif_downloader/config_loader.py
anhaltai/gbif_downloader/downloader.py
anhaltai/gbif_downloader/main.py
anhaltai/gbif_downloader/minio_log_handler.py
anhaltai/gbif_downloader/tree_list_processor.py
anhaltai/gbif_downloader/utils.py
anhaltai/gbif_downloader/crawler/__init__.py
anhaltai/gbif_downloader/crawler/base_crawler.py
anhaltai_gbif_downloader-2025.8.1.dist-info/licenses/LICENSE
anhaltai_gbif_downloader-2025.8.1.dist-info/METADATA
anhaltai_gbif_downloader-2025.8.1.dist-info/WHEEL
anhaltai_gbif_downloader-2025.8.1.dist-info/top_level.txt
anhaltai_gbif_downloader-2025.8.1.dist-info/RECORD
