Metadata-Version: 2.4
Name: anhaltai-gbif-downloader
Version: 2025.8.1
Summary: This project automatically downloads taxon-specific images from the GBIF API (https://techdocs.gbif.org/en/openapi/), processes them, and stores both images and metadata in a taxonomically organized structure in a MinIO (https://www.min.io/) bucket.
Author-email: AnhaltAI <hello@anhalt.ai>
License-Expression: MIT
Project-URL: Homepage, https://pypi.org/project/anhaltai-gbif-downloader/
Keywords: GBIF,image,downloader
Classifier: Programming Language :: Python :: 3
Classifier: Programming Language :: Python :: 3.12
Classifier: Operating System :: OS Independent
Requires-Python: >=3.12
License-File: LICENSE
Requires-Dist: python-dotenv==1.0.1
Requires-Dist: pandas==2.2.3
Requires-Dist: anhaltai_commons_minio==2025.3.5
Requires-Dist: requests==2.32.4
Requires-Dist: pillow==11.2.1
Requires-Dist: pyYAML==6.0.2
Requires-Dist: openpyxl==3.1.5
Requires-Dist: pandas-stubs==2.3.0.250703
Requires-Dist: types-requests==2.32.4.20250611
Requires-Dist: types-PyYAML==6.0.12.20250516
Provides-Extra: test
Requires-Dist: pytest>=8.4.1; extra == "test"
Requires-Dist: pytest-cov>=6.2.1; extra == "test"
Dynamic: license-file
